blrec/__init__.py
blrec/__main__.py
blrec/application.py
blrec/bili/__init__.py
blrec/bili/api.py
blrec/bili/danmaku_client.py
blrec/bili/exceptions.py
blrec/bili/helpers.py
blrec/bili/live.py
blrec/bili/live_monitor.py
blrec/bili/models.py
blrec/bili/typing.py
blrec/cli/__init__.py
blrec/cli/main.py
blrec/core/__init__.py
blrec/core/cover_downloader.py
blrec/core/danmaku_dumper.py
blrec/core/danmaku_receiver.py
blrec/core/flv_stream_recorder_impl.py
blrec/core/hls_raw_stream_recorder_impl.py
blrec/core/hls_stream_recorder_impl.py
blrec/core/metadata_provider.py
blrec/core/models.py
blrec/core/path_provider.py
blrec/core/raw_danmaku_dumper.py
blrec/core/raw_danmaku_receiver.py
blrec/core/recorder.py
blrec/core/statistics.py
blrec/core/stream_param_holder.py
blrec/core/stream_recorder.py
blrec/core/stream_recorder_impl.py
blrec/core/typing.py
blrec/core/operators/__init__.py
blrec/core/operators/connection_error_handler.py
blrec/core/operators/exception_handler.py
blrec/core/operators/progress_bar.py
blrec/core/operators/recording_monitor.py
blrec/core/operators/request_exception_handler.py
blrec/core/operators/sized_statistics.py
blrec/core/operators/stream_fetcher.py
blrec/core/operators/stream_parser.py
blrec/core/operators/stream_statistics.py
blrec/core/operators/stream_url_resolver.py
blrec/danmaku/__init__.py
blrec/danmaku/combination.py
blrec/danmaku/common.py
blrec/danmaku/concatenation.py
blrec/danmaku/helpers.py
blrec/danmaku/io.py
blrec/danmaku/models.py
blrec/danmaku/typing.py
blrec/data/message_templates/html/error.html
blrec/data/message_templates/html/live-began.html
blrec/data/message_templates/html/live-ended.html
blrec/data/message_templates/html/space-no-enough.html
blrec/data/message_templates/markdown/error.md
blrec/data/message_templates/markdown/live-began.md
blrec/data/message_templates/markdown/live-ended.md
blrec/data/message_templates/markdown/space-no-enough.md
blrec/data/message_templates/text/error.txt
blrec-1.15.0.dist-info/LICENSE
blrec-1.15.0.dist-info/METADATA
blrec-1.15.0.dist-info/WHEEL
blrec-1.15.0.dist-info/entry_points.txt
blrec-1.15.0.dist-info/top_level.txt
blrec-1.15.0.dist-info/RECORD
