Metadata-Version: 2.1
Name: blrec
Version: 1.15.0
Summary: Bilibili Live Streaming Recorder
Home-page: https://github.com/acgnhiki/blrec
Author: acgnhiki
Author-email: acgnhiki@outlook.com
License: GPLv3
Keywords: bilibili,live,danmaku,recorder
Platform: UNKNOWN
Classifier: Development Status :: 5 - Production/Stable
Classifier: Environment :: Console
Classifier: Environment :: Web Environment
Classifier: Intended Audience :: Developers
Classifier: Intended Audience :: End Users/Desktop
Classifier: License :: OSI Approved :: GNU General Public License v3 (GPLv3)
Classifier: Topic :: Internet
Classifier: Topic :: Multimedia :: Video
Classifier: Operating System :: OS Independent
Classifier: Programming Language :: Python :: 3 :: Only
Classifier: Programming Language :: Python :: 3
Classifier: Programming Language :: Python :: 3.8
Classifier: Programming Language :: Python :: 3.9
Classifier: Programming Language :: Python :: 3.10
Classifier: Programming Language :: Python :: Implementation :: CPython
Classifier: Typing :: Typed
Requires-Python: >=3.8
License-File: LICENSE
Requires-Dist: python-liquid (<2.0.0,>=1.2.1)
Requires-Dist: typing-extensions (>=3.10.0.0)
Requires-Dist: ordered-set (<5.0.0,>=4.1.0)
Requires-Dist: fastapi (<0.89.0,>=0.88.0)
Requires-Dist: email-validator (<2.0.0,>=1.1.3)
Requires-Dist: click (<8.1.0)
Requires-Dist: typer (<0.8.0,>=0.7.0)
Requires-Dist: aiohttp (<4.0.0,>=3.8.1)
Requires-Dist: requests (<3.0.0,>=2.24.0)
Requires-Dist: aiofiles (<23.0.0,>=22.1.0)
Requires-Dist: tenacity (<9.0.0,>=8.0.1)
Requires-Dist: colorama (<0.5.0,>=0.4.4)
Requires-Dist: humanize (<4.0.0,>=3.13.1)
Requires-Dist: tqdm (<5.0.0,>=4.62.3)
Requires-Dist: attrs (<22.0.0,>=21.2.0)
Requires-Dist: lxml (<5.0.0,>=4.6.4)
Requires-Dist: toml (<0.11.0,>=0.10.2)
Requires-Dist: m3u8 (<4.0.0,>=3.3.0)
Requires-Dist: av (<11.0.0,>=10.0.0)
Requires-Dist: jsonpath (==0.82)
Requires-Dist: psutil (<6.0.0,>=5.8.0)
Requires-Dist: reactivex (<5.0.0,>=4.0.0)
Requires-Dist: bitarray (<3.0.0,>=2.2.5)
Requires-Dist: brotli (<2.0.0,>=1.0.9)
Requires-Dist: brotli-asgi (<1.4.0,>=1.3.0)
Requires-Dist: uvicorn[standard] (<0.21.0,>=0.20.0)
Provides-Extra: dev
Requires-Dist: flake8 (>=4.0.1) ; extra == 'dev'
Requires-Dist: mypy (==0.910) ; extra == 'dev'
Requires-Dist: isort (>=5.10.1) ; extra == 'dev'
Requires-Dist: black (>=22.3.0) ; extra == 'dev'
Requires-Dist: autoflake (>=1.4) ; extra == 'dev'
Requires-Dist: setuptools (>=59.4.0) ; extra == 'dev'
Requires-Dist: wheel (>=0.37) ; extra == 'dev'
Requires-Dist: build (>=0.7.0) ; extra == 'dev'
Requires-Dist: twine (>=3.7.1) ; extra == 'dev'
Requires-Dist: types-requests (>=2.26.1) ; extra == 'dev'
Requires-Dist: types-aiofiles (>=0.1.7) ; extra == 'dev'
Requires-Dist: types-toml (>=0.10.1) ; extra == 'dev'
Requires-Dist: types-setuptools (>=57.4.4) ; extra == 'dev'
Provides-Extra: speedups
Requires-Dist: aiohttp[speedups] (<4.0.0,>=3.8.1) ; extra == 'speedups'
